repopack/__init__.py
repopack/__main__.py
repopack/cli.py
repopack/config.py
repopack/exceptions.py
repopack/output_generator.py
repopack/packager.py
repopack/version.py
repopack/utils/__init__.py
repopack/utils/cli_output.py
repopack/utils/file_handler.py
repopack/utils/file_manipulator.py
repopack/utils/ignore_utils.py
repopack/utils/logger.py
repopack/utils/spinner.py
repopack/utils/tree_generator.py
tests/__init__.py
tests/test_cli.py
tests/test_config.py
tests/test_file_handler.py
tests/test_ignore_utils.py
tests/test_output_generator.py
tests/test_packager.py
tests/test_tree_generator.py
repopack-0.1.4.dist-info/LICENSE
repopack-0.1.4.dist-info/METADATA
repopack-0.1.4.dist-info/WHEEL
repopack-0.1.4.dist-info/entry_points.txt
repopack-0.1.4.dist-info/top_level.txt
repopack-0.1.4.dist-info/RECORD
