Metadata-Version: 2.1
Name: repopack
Version: 0.1.4
Summary: A tool to pack repository contents into a single file for AI analysis
Home-page: https://github.com/abinthomasonline/repopack-py
Author: Abin Thomas
Author-email: abinthomasonline@gmail.com
Classifier: Programming Language :: Python :: 3
Classifier: License :: OSI Approved :: MIT License
Classifier: Operating System :: OS Independent
Requires-Python: >=3.7
License-File: LICENSE
Requires-Dist: chardet
Requires-Dist: colorama
Requires-Dist: halo
Requires-Dist: pathspec
Provides-Extra: dev
Requires-Dist: black ; extra == 'dev'
Requires-Dist: build ; extra == 'dev'
Requires-Dist: pre-commit ; extra == 'dev'
Requires-Dist: pytest ; extra == 'dev'
Requires-Dist: pytest-cov ; extra == 'dev'
Requires-Dist: twine ; extra == 'dev'
